Dockerfile
MANIFEST.in
README.md
fathom.png
mkdocs.yml
pylintrc
runtest.sh
setup.cfg
setup.py
Fathom_Workloads.egg-info/PKG-INFO
Fathom_Workloads.egg-info/SOURCES.txt
Fathom_Workloads.egg-info/dependency_links.txt
Fathom_Workloads.egg-info/not-zip-safe
Fathom_Workloads.egg-info/top_level.txt
docs/faq.md
docs/index.md
docs/models.md
docs/quickstart.md
docs/assets/fathom.css
docs/assets/fix_search.js
docs/assets/water-header.png
fathom/__init__.py
fathom/dataset.py
fathom/nn.py
fathom/alexnet/__init__.py
fathom/alexnet/alexnet.py
fathom/autoenc/__init__.py
fathom/autoenc/autoenc.py
fathom/autoenc/variational.py
fathom/deepq/__init__.py
fathom/deepq/database.py
fathom/deepq/deepq.py
fathom/deepq/emulator.py
fathom/imagenet/__init__.py
fathom/imagenet/image_processing.py
fathom/imagenet/imagenet.py
fathom/imagenet/mnist.py
fathom/memnet/__init__.py
fathom/memnet/data_utils.py
fathom/memnet/memnet.py
fathom/residual/__init__.py
fathom/residual/residual.py
fathom/seq2seq/__init__.py
fathom/seq2seq/data_utils.py
fathom/seq2seq/seq2seq.py
fathom/speech/__init__.py
fathom/speech/phoneme.py
fathom/speech/preproc.py
fathom/speech/speech.py
fathom/vgg/__init__.py
fathom/vgg/vgg.py
test/test_basics.py